heat_dashboard/__init__.py
heat_dashboard/exceptions.py
heat_dashboard/api/__init__.py
heat_dashboard/api/heat.py
heat_dashboard/api/rest/__init__.py
heat_dashboard/api/rest/heat.py
heat_dashboard/conf/heat_policy.yaml
heat_dashboard/conf/default_policies/heat.yaml
heat_dashboard/content/__init__.py
heat_dashboard/content/resource_types/__init__.py
heat_dashboard/content/resource_types/panel.py
heat_dashboard/content/resource_types/tables.py
heat_dashboard/content/resource_types/tabs.py
heat_dashboard/content/resource_types/urls.py
heat_dashboard/content/resource_types/views.py
heat_dashboard/content/resource_types/templates/resource_types/_details.html
heat_dashboard/content/resource_types/templates/stacks.resource_types/_details.html
heat_dashboard/content/stacks/__init__.py
heat_dashboard/content/stacks/api.py
heat_dashboard/content/stacks/forms.py
heat_dashboard/content/stacks/mappings.py
heat_dashboard/content/stacks/panel.py
heat_dashboard/content/stacks/sro.py
heat_dashboard/content/stacks/tables.py
heat_dashboard/content/stacks/tabs.py
heat_dashboard/content/stacks/urls.py
heat_dashboard/content/stacks/views.py
heat_dashboard/content/stacks/templates/stacks/_change_template.html
heat_dashboard/content/stacks/templates/stacks/_create.html
heat_dashboard/content/stacks/templates/stacks/_detail_events.html
heat_dashboard/content/stacks/templates/stacks/_detail_overview.html
heat_dashboard/content/stacks/templates/stacks/_detail_resources.html
heat_dashboard/content/stacks/templates/stacks/_detail_topology.html
heat_dashboard/content/stacks/templates/stacks/_preview.html
heat_dashboard/content/stacks/templates/stacks/_preview_details.html
heat_dashboard/content/stacks/templates/stacks/_preview_template.html
heat_dashboard/content/stacks/templates/stacks/_resource_info.html
heat_dashboard/content/stacks/templates/stacks/_resource_overview.html
heat_dashboard/content/stacks/templates/stacks/_select_template.html
heat_dashboard-14.0.0.dist-info/AUTHORS
heat_dashboard-14.0.0.dist-info/LICENSE
heat_dashboard-14.0.0.dist-info/METADATA
heat_dashboard-14.0.0.dist-info/WHEEL
heat_dashboard-14.0.0.dist-info/pbr.json
heat_dashboard-14.0.0.dist-info/top_level.txt
heat_dashboard-14.0.0.dist-info/RECORD
