Metadata-Version: 2.1
Name: heat-dashboard
Version: 14.0.0
Summary: Heat Management Dashboard
Home-page: https://docs.openstack.org/heat-dashboard/latest/
Author: OpenStack
Author-email: openstack-discuss@lists.openstack.org
Classifier: Environment :: OpenStack
Classifier: Intended Audience :: Information Technology
Classifier: Intended Audience :: System Administrators
Classifier: License :: OSI Approved :: Apache Software License
Classifier: Operating System :: POSIX :: Linux
Classifier: Programming Language :: Python
Classifier: Programming Language :: Python :: Implementation :: CPython
Classifier: Programming Language :: Python :: 3 :: Only
Classifier: Programming Language :: Python :: 3
Classifier: Programming Language :: Python :: 3.10
Classifier: Programming Language :: Python :: 3.11
Classifier: Programming Language :: Python :: 3.12
Requires-Python: >=3.10
License-File: LICENSE
License-File: AUTHORS
Requires-Dist: pbr >=5.5.0
Requires-Dist: python-heatclient >=1.10.0
Requires-Dist: horizon >=25.0.0
Requires-Dist: xstatic-angular-uuid >=0.0.4.0
Requires-Dist: xstatic-angular-vis >=4.16.0.0
Requires-Dist: xstatic-filesaver >=1.3.2.0
Requires-Dist: xstatic-js-yaml >=3.8.1.0
Requires-Dist: xstatic-json2yaml >=0.1.1.0
